odoo10_addon_barcodes_ean14-10.0.1.0.1-nspkg.pth
odoo/addons/barcodes_ean14/README.rst
odoo/addons/barcodes_ean14/__init__.py
odoo/addons/barcodes_ean14/__manifest__.py
odoo/addons/barcodes_ean14/i18n/barcodes_ean14.pot
odoo/addons/barcodes_ean14/i18n/es.po
odoo/addons/barcodes_ean14/i18n/es_ES.po
odoo/addons/barcodes_ean14/i18n/fr.po
odoo/addons/barcodes_ean14/i18n/hr.po
odoo/addons/barcodes_ean14/i18n/hr_HR.po
odoo/addons/barcodes_ean14/i18n/nl_NL.po
odoo/addons/barcodes_ean14/models/__init__.py
odoo/addons/barcodes_ean14/models/barcode_nomenclature.py
odoo/addons/barcodes_ean14/models/barcode_rule.py
odoo/addons/barcodes_ean14/static/description/icon.png
odoo/addons/barcodes_ean14/static/src/js/barcode_parser.js
odoo/addons/barcodes_ean14/static/tests/js/barcode_parser.js
odoo/addons/barcodes_ean14/tests/__init__.py
odoo/addons/barcodes_ean14/tests/test_barcode_nomenclature.py
odoo/addons/barcodes_ean14/views/assets.xml
odoo10_addon_barcodes_ean14-10.0.1.0.1.dist-info/METADATA
odoo10_addon_barcodes_ean14-10.0.1.0.1.dist-info/WHEEL
odoo10_addon_barcodes_ean14-10.0.1.0.1.dist-info/namespace_packages.txt
odoo10_addon_barcodes_ean14-10.0.1.0.1.dist-info/top_level.txt
odoo10_addon_barcodes_ean14-10.0.1.0.1.dist-info/RECORD
